{
    "boxes": [
        {
            "type": "polygon",
            "label": "crop",
            "x": "225.0000",
            "y": "277.5000",
            "width": "364.0000",
            "height": "305.0000",
            "points": [
                [
                    251,
                    125
                ],
                [
                    262,
                    129
                ],
                [
                    273,
                    173
                ],
                [
                    275,
                    197
                ],
                [
                    283,
                    218
                ],
                [
                    281,
                    235
                ],
                [
                    293,
                    236
                ],
                [
                    336,
                    212
                ],
                [
                    382,
                    218
                ],
                [
                    402,
                    226
                ],
                [
                    405,
                    232
                ],
                [
                    403,
                    248
                ],
                [
                    407,
                    259
                ],
                [
                    397,
                    279
                ],
                [
                    358,
                    296
                ],
                [
                    317,
                    301
                ],
                [
                    303,
                    295
                ],
                [
                    291,
                    304
                ],
                [
                    290,
                    311
                ],
                [
                    298,
                    322
                ],
                [
                    302,
                    366
                ],
                [
                    300,
                    397
                ],
                [
                    304,
                    426
                ],
                [
                    300,
                    430
                ],
                [
                    282,
                    426
                ],
                [
                    268,
                    413
                ],
                [
                    251,
                    405
                ],
                [
                    218,
                    376
                ],
                [
                    210,
                    362
                ],
                [
                    199,
                    356
                ],
                [
                    194,
                    339
                ],
                [
                    201,
                    324
                ],
                [
                    181,
                    319
                ],
                [
                    183,
                    309
                ],
                [
                    196,
                    296
                ],
                [
                    190,
                    285
                ],
                [
                    162,
                    283
                ],
                [
                    130,
                    300
                ],
                [
                    108,
                    304
                ],
                [
                    71,
                    299
                ],
                [
                    46,
                    286
                ],
                [
                    43,
                    281
                ],
                [
                    43,
                    267
                ],
                [
                    55,
                    253
                ],
                [
                    57,
                    235
                ],
                [
                    77,
                    223
                ],
                [
                    126,
                    222
                ],
                [
                    150,
                    232
                ],
                [
                    163,
                    246
                ],
                [
                    182,
                    239
                ],
                [
                    184,
                    232
                ],
                [
                    177,
                    219
                ],
                [
                    190,
                    214
                ],
                [
                    199,
                    183
                ],
                [
                    222,
                    153
                ]
            ]
        }
    ],
    "height": 512,
    "key": "agri_0_249.jpeg",
    "width": 512
}