{
    "boxes": [
        {
            "type": "polygon",
            "label": "crop",
            "x": "270.0000",
            "y": "248.0000",
            "width": "440.0000",
            "height": "346.0000",
            "points": [
                [
                    282,
                    75
                ],
                [
                    291,
                    77
                ],
                [
                    307,
                    96
                ],
                [
                    319,
                    122
                ],
                [
                    293,
                    168
                ],
                [
                    293,
                    176
                ],
                [
                    310,
                    187
                ],
                [
                    324,
                    182
                ],
                [
                    344,
                    185
                ],
                [
                    348,
                    191
                ],
                [
                    372,
                    199
                ],
                [
                    415,
                    225
                ],
                [
                    469,
                    279
                ],
                [
                    486,
                    302
                ],
                [
                    490,
                    314
                ],
                [
                    471,
                    319
                ],
                [
                    405,
                    320
                ],
                [
                    366,
                    317
                ],
                [
                    322,
                    307
                ],
                [
                    309,
                    315
                ],
                [
                    276,
                    301
                ],
                [
                    263,
                    284
                ],
                [
                    243,
                    283
                ],
                [
                    228,
                    300
                ],
                [
                    223,
                    312
                ],
                [
                    224,
                    322
                ],
                [
                    231,
                    329
                ],
                [
                    236,
                    343
                ],
                [
                    235,
                    363
                ],
                [
                    229,
                    379
                ],
                [
                    216,
                    397
                ],
                [
                    195,
                    410
                ],
                [
                    186,
                    409
                ],
                [
                    174,
                    400
                ],
                [
                    173,
                    415
                ],
                [
                    160,
                    421
                ],
                [
                    147,
                    405
                ],
                [
                    136,
                    382
                ],
                [
                    133,
                    337
                ],
                [
                    145,
                    316
                ],
                [
                    164,
                    299
                ],
                [
                    184,
                    261
                ],
                [
                    183,
                    252
                ],
                [
                    158,
                    250
                ],
                [
                    123,
                    236
                ],
                [
                    95,
                    210
                ],
                [
                    65,
                    178
                ],
                [
                    61,
                    162
                ],
                [
                    50,
                    143
                ],
                [
                    50,
                    120
                ],
                [
                    61,
                    113
                ],
                [
                    100,
                    111
                ],
                [
                    119,
                    114
                ],
                [
                    149,
                    126
                ],
                [
                    167,
                    126
                ],
                [
                    180,
                    135
                ],
                [
                    188,
                    135
                ],
                [
                    206,
                    165
                ],
                [
                    215,
                    166
                ],
                [
                    224,
                    148
                ],
                [
                    236,
                    136
                ],
                [
                    237,
                    129
                ],
                [
                    231,
                    124
                ],
                [
                    232,
                    116
                ],
                [
                    253,
                    94
                ]
            ]
        }
    ],
    "height": 512,
    "key": "agri_0_4356.jpeg",
    "width": 512
}