{
    "boxes": [
        {
            "type": "polygon",
            "label": "crop",
            "x": "262.0000",
            "y": "241.0000",
            "width": "388.0000",
            "height": "452.0000",
            "points": [
                [
                    238,
                    15
                ],
                [
                    258,
                    32
                ],
                [
                    277,
                    65
                ],
                [
                    300,
                    140
                ],
                [
                    298,
                    183
                ],
                [
                    293,
                    201
                ],
                [
                    273,
                    224
                ],
                [
                    251,
                    240
                ],
                [
                    253,
                    246
                ],
                [
                    267,
                    248
                ],
                [
                    300,
                    229
                ],
                [
                    310,
                    221
                ],
                [
                    329,
                    192
                ],
                [
                    367,
                    172
                ],
                [
                    428,
                    163
                ],
                [
                    449,
                    169
                ],
                [
                    456,
                    182
                ],
                [
                    456,
                    201
                ],
                [
                    440,
                    214
                ],
                [
                    435,
                    242
                ],
                [
                    419,
                    264
                ],
                [
                    392,
                    283
                ],
                [
                    386,
                    296
                ],
                [
                    341,
                    311
                ],
                [
                    347,
                    338
                ],
                [
                    362,
                    350
                ],
                [
                    378,
                    381
                ],
                [
                    393,
                    397
                ],
                [
                    394,
                    414
                ],
                [
                    400,
                    425
                ],
                [
                    400,
                    434
                ],
                [
                    388,
                    452
                ],
                [
                    371,
                    453
                ],
                [
                    370,
                    467
                ],
                [
                    347,
                    461
                ],
                [
                    336,
                    454
                ],
                [
                    316,
                    430
                ],
                [
                    278,
                    395
                ],
                [
                    270,
                    374
                ],
                [
                    249,
                    343
                ],
                [
                    248,
                    329
                ],
                [
                    236,
                    316
                ],
                [
                    225,
                    343
                ],
                [
                    202,
                    362
                ],
                [
                    186,
                    368
                ],
                [
                    140,
                    375
                ],
                [
                    85,
                    375
                ],
                [
                    68,
                    369
                ],
                [
                    72,
                    356
                ],
                [
                    83,
                    345
                ],
                [
                    70,
                    324
                ],
                [
                    131,
                    302
                ],
                [
                    178,
                    259
                ],
                [
                    196,
                    257
                ],
                [
                    208,
                    261
                ],
                [
                    204,
                    246
                ],
                [
                    193,
                    229
                ],
                [
                    206,
                    221
                ],
                [
                    199,
                    204
                ],
                [
                    196,
                    178
                ],
                [
                    197,
                    154
                ],
                [
                    206,
                    119
                ],
                [
                    205,
                    73
                ],
                [
                    213,
                    38
                ],
                [
                    222,
                    32
                ],
                [
                    233,
                    16
                ]
            ]
        }
    ],
    "height": 512,
    "key": "agri_0_9888.jpeg",
    "width": 512
}